netmiko/__init__.py
netmiko/base_connection.py
netmiko/cisco_base_connection.py
netmiko/netmiko_globals.py
netmiko/scp_functions.py
netmiko/scp_handler.py
netmiko/snmp_autodetect.py
netmiko/ssh_autodetect.py
netmiko/ssh_dispatcher.py
netmiko/ssh_exception.py
netmiko/utilities.py
netmiko/_textfsm/__init__.py
netmiko/_textfsm/_clitable.py
netmiko/_textfsm/_terminal.py
netmiko/_textfsm/_texttable.py
netmiko/a10/__init__.py
netmiko/a10/a10_ssh.py
netmiko/accedian/__init__.py
netmiko/accedian/accedian_ssh.py
netmiko/adtran/__init__.py
netmiko/adtran/adtran.py
netmiko/alcatel/__init__.py
netmiko/alcatel/alcatel_aos_ssh.py
netmiko/allied_telesis/__init__.py
netmiko/allied_telesis/allied_telesis_awplus.py
netmiko/apresia/__init__.py
netmiko/apresia/apresia_aeos.py
netmiko/arista/__init__.py
netmiko/arista/arista.py
netmiko/aruba/__init__.py
netmiko/aruba/aruba_ssh.py
netmiko/broadcom/__init__.py
netmiko/broadcom/broadcom_icos_ssh.py
netmiko/brocade/__init__.py
netmiko/brocade/brocade_fos_ssh.py
netmiko/calix/__init__.py
netmiko/calix/calix_b6.py
netmiko/cdot/__init__.py
netmiko/cdot/cdot_cros_ssh.py
netmiko/centec/__init__.py
netmiko/centec/centec_os.py
netmiko/checkpoint/__init__.py
netmiko/checkpoint/checkpoint_gaia_ssh.py
netmiko/ciena/__init__.py
netmiko/ciena/ciena_saos.py
netmiko/cisco/__init__.py
netmiko/cisco/cisco_asa_ssh.py
netmiko/cisco/cisco_ftd_ssh.py
netmiko/cisco/cisco_ios.py
netmiko/cisco/cisco_nxos_ssh.py
netmiko/cisco/cisco_s300.py
netmiko/cisco/cisco_tp_tcce.py
netmiko/cisco/cisco_wlc_ssh.py
netmiko/cisco/cisco_xr.py
netmiko/citrix/__init__.py
netmiko/citrix/netscaler_ssh.py
netmiko/cloudgenix/__init__.py
netmiko/cloudgenix/cloudgenix_ion.py
netmiko/coriant/__init__.py
netmiko/coriant/coriant_ssh.py
netmiko/dell/__init__.py
netmiko/dell/dell_dnos6.py
netmiko/dell/dell_force10_ssh.py
netmiko/dell/dell_isilon_ssh.py
netmiko/dell/dell_os10_ssh.py
netmiko/dell/dell_powerconnect.py
netmiko/dlink/__init__.py
netmiko/dlink/dlink_ds.py
netmiko/eltex/__init__.py
netmiko_bsh-3.4.0.dist-info/LICENSE
netmiko_bsh-3.4.0.dist-info/METADATA
netmiko_bsh-3.4.0.dist-info/WHEEL
netmiko_bsh-3.4.0.dist-info/top_level.txt
netmiko_bsh-3.4.0.dist-info/RECORD
