Metadata-Version: 2.1
Name: netmiko-bsh
Version: 3.4.0
Summary: Multi-vendor library to simplify Paramiko SSH connections to network devices
Home-page: https://github.com/bsh-developers/netmiko-bsh
Author: Kirk Byers, BSH
Author-email: ktbyers@twb-tech.com, opensource@bsh.ru
License: MIT
Platform: UNKNOWN
Classifier: License :: OSI Approved :: MIT License
Classifier: Programming Language :: Python :: 3
Classifier: Programming Language :: Python :: 3.6
Classifier: Programming Language :: Python :: 3.7
Classifier: Programming Language :: Python :: 3.8
Classifier: Programming Language :: Python :: 3.9
License-File: LICENSE
Requires-Dist: setuptools (>=38.4.0)
Requires-Dist: paramiko (>=2.6.0)
Requires-Dist: scp (>=0.13.2)
Requires-Dist: tenacity
Requires-Dist: ntc-templates-bsh
Requires-Dist: pyserial
Requires-Dist: importlib-resources ; python_version < "3.7"
Provides-Extra: test
Requires-Dist: pyyaml (>=5.1.2) ; extra == 'test'
Requires-Dist: pytest (>=5.1.2) ; extra == 'test'
